yuku/Yuku.py
yuku/__init__.py
yuku/_version.py
yuku-0.0.7.data/scripts/yuku_run
yuku-0.0.7.dist-info/licenses/LICENSE
yuku-0.0.7.dist-info/METADATA
yuku-0.0.7.dist-info/WHEEL
yuku-0.0.7.dist-info/top_level.txt
yuku-0.0.7.dist-info/RECORD
