Metadata-Version: 2.4
Name: Yuku
Version: 0.0.7
Summary: Scienti Open Data
Home-page: https://github.com/colav/Yuku
Author: Colav
Author-email: colav@udea.edu.co
License: BSD
License-File: LICENSE
Requires-Dist: pymongo>=3.10.1
Requires-Dist: numpy
Requires-Dist: pandas
Requires-Dist: requests>=2.22.0
Requires-Dist: sodapy
Requires-Dist: beautifulsoup4
Requires-Dist: lxml
Dynamic: author
Dynamic: author-email
Dynamic: description
Dynamic: description-content-type
Dynamic: home-page
Dynamic: license
Dynamic: license-file
Dynamic: requires-dist
Dynamic: summary
